marquedown/__init__.py
marquedown/__main__.py
marquedown/bblike.py
marquedown/citation.py
marquedown/commands/__init__.py
marquedown/commands/render.py
marquedown/labellist.py
marquedown/qr.py
marquedown/tagtools.py
marquedown/video.py
marquedown-0.12.0.dist-info/LICENSE
marquedown-0.12.0.dist-info/METADATA
marquedown-0.12.0.dist-info/WHEEL
marquedown-0.12.0.dist-info/RECORD
