Metadata-Version: 2.1
Name: marquedown
Version: 0.12.0
Summary: Extending Markdown further by adding a few more useful notations.
Home-page: https://gitlab.com/deepadmax/marquedown
License: GPL-3.0-or-later
Author: Maximillian Strand
Author-email: maxi@millian.se
Requires-Python: >=3.10,<4.0
Classifier: License :: OSI Approved :: GNU General Public License v3 or later (GPLv3+)
Classifier: Programming Language :: Python :: 3
Classifier: Programming Language :: Python :: 3.10
Classifier: Programming Language :: Python :: 3.11
Requires-Dist: PyYAML (>=6.0,<7.0)
Requires-Dist: markdown2 (>=2.4.8,<3.0.0)
Requires-Dist: qrcode[pil] (>=7.3.1,<8.0.0)
Project-URL: Repository, https://gitlab.com/deepadmax/marquedown
